gesserit/__init__.py
gesserit/core.py
gesserit/static/gesserit.svg
gesserit/templates/index.html
gesserit-0.3.1.dist-info/WHEEL
gesserit-0.3.1.dist-info/METADATA
gesserit-0.3.1.dist-info/RECORD
