Metadata-Version: 2.3
Name: gesserit
Version: 0.3.1
Summary: Inspect retrieval results
Author: Yoni Gottesman
Author-email: Yoni Gottesman <yonigo10@gmail.com>
Requires-Dist: fastapi>=0.109
Requires-Dist: jinja2>=3.1.6
Requires-Dist: pillow>=11.3.0
Requires-Dist: python-multipart>=0.0.20
Requires-Dist: uvicorn>=0.22
Requires-Python: >=3.9
Project-URL: Repository, https://github.com/yonigottesman/gesserit
